langchain_predictionguard/ChatPredictionGuard.py
langchain_predictionguard/PredictionGuard.py
langchain_predictionguard/PredictionGuardEmbeddings.py
langchain_predictionguard/PredictionGuardRerank.py
langchain_predictionguard/__init__.py
langchain_predictionguard/utils.py
langchain_predictionguard-0.3.0.dist-info/LICENSE
langchain_predictionguard-0.3.0.dist-info/METADATA
langchain_predictionguard-0.3.0.dist-info/WHEEL
langchain_predictionguard-0.3.0.dist-info/RECORD
