Metadata-Version: 2.3
Name: langchain-predictionguard
Version: 0.3.0
Summary: Create controlled and compliant AI systems with PredictionGuard and LangChain
License: MIT
Author: Jacob Mansdorfer
Author-email: jacob@predictionguard.com
Requires-Python: >=3.9,<4.0
Classifier: License :: OSI Approved :: MIT License
Classifier: Programming Language :: Python :: 3
Classifier: Programming Language :: Python :: 3.9
Classifier: Programming Language :: Python :: 3.10
Classifier: Programming Language :: Python :: 3.11
Classifier: Programming Language :: Python :: 3.12
Classifier: Programming Language :: Python :: 3.13
Requires-Dist: langchain-core (>=0.3.27,<0.4.0)
Requires-Dist: predictionguard (>=2.7.0,<3.0.0)
Project-URL: Homepage, https://predictionguard.com
Project-URL: Repository, https://www.github.com/predictionguard/langchain-predictionguard
